LICENSE
MANIFEST.in
readme_for_pypi.md
setup.cfg
setup.py
4logik_python_rest_client.egg-info/PKG-INFO
4logik_python_rest_client.egg-info/SOURCES.txt
4logik_python_rest_client.egg-info/dependency_links.txt
4logik_python_rest_client.egg-info/requires.txt
4logik_python_rest_client.egg-info/top_level.txt
py4logik_python_rest_client/__init__.py
py4logik_python_rest_client/endpoint_caller.py