Metadata-Version: 2.1
Name: 4logik-python-rest-client
Version: 1.0.2
Summary: Execute microservice endpoint using HTTP REST
Home-page: https://www.4logik.com/
Author: Eugenia Morales
Author-email: eugeniamorales251@gmail.com
License: MIT
Keywords: python project
Platform: UNKNOWN
Classifier: License :: OSI Approved :: MIT License
Classifier: Programming Language :: Python
Classifier: Programming Language :: Python :: 3
